ople/__init__.py
ople/client.py
ople-1.0.1.data/scripts/ople-client
ople-1.0.1.dist-info/LICENSE
ople-1.0.1.dist-info/METADATA
ople-1.0.1.dist-info/WHEEL
ople-1.0.1.dist-info/top_level.txt
ople-1.0.1.dist-info/RECORD
