Metadata-Version: 2.1
Name: ople
Version: 1.0.1
Summary: Ople Python Client
Home-page: UNKNOWN
Author: Ople Inc.
Author-email: info@ople.ai
License: UNKNOWN
Platform: UNKNOWN
Classifier: Programming Language :: Python :: 3
Classifier: License :: OSI Approved :: MIT License
Classifier: Operating System :: OS Independent
Requires-Python: >=3.6
